gui.py
quinten_gui-0.1.2.dist-info/LICENSE
quinten_gui-0.1.2.dist-info/METADATA
quinten_gui-0.1.2.dist-info/WHEEL
quinten_gui-0.1.2.dist-info/top_level.txt
quinten_gui-0.1.2.dist-info/RECORD
