Metadata-Version: 2.1
Name: quinten-gui
Version: 0.1.2
Author-email: Quinten Roets <qdr2104@columbia.edu>
License: MIT
Project-URL: Source Code, https://github.com/quintenroets/gui
Requires-Python: >=3.10
License-File: LICENSE
Requires-Dist: powercli
Requires-Dist: yad
Provides-Extra: dev
Requires-Dist: pre-commit ; extra == 'dev'
Provides-Extra: test
Requires-Dist: pytest ; extra == 'test'
